{   
    "cdnc":"CDNC management system",
    "en":"English",
    "zh":"Chinese",
    "login":"Login",
    "cdncManagementSystem":"CDNC Management System",
    "userName":"UserName",
    "userName_placeholder":"Please enter userName",
    "password":"Password",
    "password_placeholder":"Please enter password",
    "code":"Code",
    "code_placeholder":"Please enter code",
    "authenticationMmanagement":"AuthenticationMmanagement",
    "contentManagement":"ContentManagement",
    "strategyManagement":"StrategyManagement",
    "cacheStrategyManagement":"CacheStrategyManagement",
    "viewManagement":"ViewManagement",
    "logReport":"LogReport",
    "securityManagement":"SecurityManagement",
    "systemConfig":"SystemConfig",
    "logManagement":"LogManagement",

    "pagingOptions":{
        "allTotal":"Found records",
        "pages":"Pages",
        "unit": "bar/page",
        "page":"page",
        "jump":"jump",
        "bar":"bar"
    },
    "languageSet":"LanguageSet",
    "set":"Set",
    "exit":"Exit",
    "ok":"OK",
    "submit":"submit",
    "save":"save",
    "return":"return",
    "tip_title":"Dip",
    "selectTime":"SelectTime",
    "createTime":"CreateTime",
    "updateTime":"UpdateTime",
    "loading":"loading",
    "all":"all",
    "noData":"noData",
    "pleaseChoose":"Please choose",
    "selected":"selected",
    "bar":"bar",
    "time":"time",
    "no_data":"No Data",
    "optional":"（optional）",
    "fiberhome_copyright":"FiberHome copyright",
    "openOptional":"openOptional",
    "closeOptional":"closeOptional",
    "watch":"watch",
    "openWatch":"openWatch",
    "closeWatch":"closeWatch",

    "add":"add",
    "add_S":"add success",
    "add_F":"add fail",
    "cancel":"Cancel",
    "isCancel":"Do you want to cancel",
    "cancel_S":"cancel success",
    "cancel_F":"cancel fail",
    "modify":"modify",
    "modify_S":"modify success",
    "modify_F":"modify fail",
    "modifyMore":"modifyMore",
    "delete":"delete",
    "delete_S":"delete success",
    "delete_F":"delete fail",
    "deleteMore":"deleteMore",
    "isDelete":"Do you want to delete？",
    "isDeleteMore":"Do you want to delete more？",
    "isDeleteConfig":"Do you want to delete this config？",
    "retry":"retry",
    "isRetry":"Do you want to retry？",
    "retry_S":"retry success",
    "retry_F":"retry fail",
    "synchro":"synchro",
    "isSynchro":"Do you want to synchro？",
    "synchro_S":"synchro success",
    "synchro_F":"synchro fail",
    "issued":"issued",
    "issued_S":"issued success",
    "issued_F":"issued fail",
    "issuedMore":"issuedMore",
    "issuedAll":"issuedAll",
    "isIssuedMore":"Do you want to issued more？",
    "isIssuedAll":"Do you want to issued all？",
    "clear":"clear",
    "isClear":"Do you want to clear？",
    "clear_S":"clear success",
    "clear_F":"clear fail",
    "config":"config",
    "configMore":"configMore",

    "search":"Search",
    "edit":"add/modify",
    "addConfig":"addConfig",
    "operation":"operation",
    "open":"open",
    "close":"close",
	"import":"import",
    "export":"export",
    "upload":"upload",
    "uploadFile":"uploadFile",
    "upload_S":"upload success",
    "upload_F":"upload fail",
    "upload_L":"uploading...",
    "upload_tip":"Click or drag files to upload",
    "importFile":"importFile",
    "importMore":"importMore",
    "importFile_S":"importFile success",
    "importFile_F":"importFile fail",
    "interfaceError":"Interface error",
    "requestError":"Request error",
    "responseError":"Response error",
    "responseError_400":"Server cannot understand the request format",
    "responseError_401":"Server request unauthorized",
    "responseError_403":"Server Access Disallowed",
    "responseError_404":"Interface not found on server",
    "responseError_500":"Server error",
    "responseError_503":"Server is temporarily unable to process requests",
    "IP":"IP",
    "type":"type",
    "name":"name",
    "need":"need",
    "noNeed":"noNeed",
    "nothing":"nothing",
    "yes":"yes",
    "no":"no",
    "not":"not",
    "node":"node",
    "nodeID":"nodeID",
    "nodeName":"nodeName",
    "group":"group",
    "groupID":"groupID",
    "groupName":"groupName",
    "ip":"ip",
    "ip_err":"IP format error",
    "ipv6_err":"IPV6 format error",
    "port":"port",
    "port_err":"Port format error",
    "file_noExist":"File does not exist",


    "authority":"Authentication Strategy",
    "CPID":"CPID",
    "domain":"domain",
    "authType":"authType",
    "fileType":"fileType",
    "keyValue":"keyValue",
    "keyVersion":"keyVersion",
    "keyEffectiveDate":"keyEffectiveDate",
    "closeAuthority":"closeAuthority",
    "localAuthority":"localAuthority",
    "secondAuthority":"secondAuthority",
    "authority_tip":"Notes：add、modify will send messages to all SNS nodes",
    "authority_del_tip":"Delete will send messages to all SNS nodes。",

    "safeChain":"SecurityChain Strategy",
    "authID":"authID",
    "authIDFormat":"authID is less than 2147483647 non-zero start number",
    "authName":"authName",
    "templateID":"templateID",
    "templateName":"templateName",
    "authSwitch":"authSwitch",
    "dualTokenValidTime":"dualTokenValidTime",
    "masterIndexSecurity":"masterIndexSecurity",
    "rateIndexSecurity":"rateIndexSecurity",
    "segmentalFileSecurity":"segmentalFileSecurity",
    "masterIndexTimestampCheck":"masterIndexTimestampCheck",
    "rateIndexTimestampCheck":"rateIndexTimestampCheck",
    "segmentalFileTimestampCheck":"segmentalFileTimestampCheck",
    "masterIndexURLValidTime":"masterIndexURLValidTime",
    "rateIndexURLValidTime":"rateIndexURLValidTime",
    "segmentalFileURLValidTime":"segmentalFileURLValidTime",
    "dwnldFileSecurity":"dwnldFileSecurity",
    "dwnldFileTimestampCheck":"dwnldFileTimestampCheck",
    "dwnldFileURLValidTime":"dwnldFileURLValidTime",
    "ipvalidMode":"ipvalidMode",
    "ipvalidMode_1":"Mandatory check IP",
    "ipvalidMode_2":"Non check IP",
    "ipvalidMode_3":"Preemptive parity check",
    "migu_AES":"migu_AES chain",


    "globalSchedulingS":"GlobalScheduling Strategy",
    "status":"status",
    "status_0":"deactivation",
    "status_1":"activation",
    "ttl":"TTL of domain",
    "policy":"policy",
    "policy_t0":"Geographically based approach",
    "policy_t1":"Content based distribution",
    "policy_t2":"Based on domain name QoS and CP level",
    "policy_t3":"Content hotspot creation",
    "policy_t4":"Based on node health",
    "policy_t5":"Weighted strategy",
    "CCSNodeList":"CCSNodeList",
    "SNSNodeList":"SNSNodeList",
    "LTCNodeList":"LTCNodeList",
    "dispatchGroupID":"dispatchGroupID",
    "dispatchGroupName":"dispatchGroupName",
    "weight":"weight",

    "globalSchedulingD":"GlobalScheduling Domain",
    "globalSchedulingD_tip":"Notes：add、modify will issued",
    "globalSchedulingD_del_tip":"Delete will issued。",

    "areaSchedulingS":"AreaScheduling Strategy",
    "policy_t6":"Business sharing",
    "redirectFormat":"redirectFormat",
    "redirectFormat_t1":"Replace original Host with target Host",
    "redirectFormat_t2":"Insert the target Host in front of the original Host",
    "clientList":"clientList",
    "ipAddr":"ipAddr",
    "ipv6Addr":"ipv6Addr",
    "mask":"mask",
    "nodeList":"nodeList",
    "groupIP":"groupIP",
    "groupIPv6":"groupIPv6",
    "serviceList":"serviceList",
    "nodeORclient":"Domain and clientList must fill in one",
    "domainWrap":"Exchange between domain and domain",
    "selectProvince":"Please select province",
    "considerations":"Considerations",
    "areaSchedulingS_tip1":"Issued is global issued，provinces as units",
    "areaSchedulingS_tip2":"The provinces has no schedulingPolicy，issued will delete the existing config on the network element",

    "localSchedulingS":"LocalScheduling Strategy",
    "listType":"listType",
    "blacklist":"blacklist",
    "whitelist":"whitelist",
    "validity":"validity",
    "validityTip":"Please input an integer less than 16 bits, 0 for permanence",
    
    "cacheStrategy":"Cache Strategy",

    "resourceStrategy":"Resource Strategy",
    "dynamicResourceConfig":"dynamicResourceConfig",
    "activeTCS":"activeTCS",
    "activeTCSv6":"activeTCSv6",
    "backupTCS":"backupTCS",
    "backupTCSv6":"backupTCSv6",
    "staticResourceConfig":"staticResourceConfig",
    "sourceList":"sourceList",
    "sourceIP":"sourceIP",
    "sourceIPv6":"sourceIPv6",

    "cp":"CP",
    "cpManagement":"CP management",
    "instruction":"instruction",
    "instruction_0":"add or modify",
    "instruction_1":"delete",
    "cpName":"cpName",
    "domainList":"domainList",
    "domainName":"domainName",
    "address":"address",
    "phone":"phone",
    "contactName":"contactName",
    "isSign":"isSign",
    "priority":"priority",
    "priority_0":"low",
    "priority_1":"middle",
    "priority_2":"high",

    "domainManagement":"Domain Management",
    "cpdomainConfig":"CP domainConfig",
    "domainManagement_tip":"Notes：add、modify will issued",
    "domainManagement_del_tip":"Delete will issued",

    "ipDatabase":"IP Database",
    "addIp":"addIp",
    "addIpRange":"addIpRange",
    "startIp":"startIp",
    "endIp":"endIp",
    "addIpv6":"addIpv6",
    "addIpv6Range":"addIpv6Range",
    "startIpv6":"startIpv6",
    "endIpv6":"endIpv6",
    "IPRangeTip":"Please input valid ip address or ip address range.",
    "IPv6RangeTip":"Please input valid ipv6 address or ipv6 address range.",
    "downloadTemplate":"download template",
    "selectFile":"select file",
    "importIPDispatchList":"import IP dispatch List",
    "fileName":"file Nmae",
    "fileFormatError":"The file is not in the correct format,please select excel file.",
    "fileFormatError_C":"The file is not in the correct format",

    "auxiliaryStrategy":"Auxiliary Strategy",
    "priority_b":"bottom",
    "priority_f":"first",
    "dynamicResource":"dynamicResource",
    "staticResource":"staticResource",
    "staticIP":"staticIP",
    "staticIPv6":"staticIPv6",
    "dynamicIP":"dynamicIP",
    "dynamicIPv6":"dynamicIPv6",
    "cname":"cname",
    "nameserverIP":"nameserverIP",
    "ipv4List":"IPv4List",
    "ipv6List":"IPv6List",
    "ipStart":"ipStart",
    "ipEnd":"ipEnd",
    "auxiliaryStrategy_ipTip":"Format：startIp-endIp or ip/mask",
    "auxiliaryStrategy_ipv6Tip":"Format：startIpv6-endIpv6 or ipv6/mask",

    "blackWhiteList":"BlackWhite List",
    "blackList":"blackList",
    "whiteList":"whiteList",
    "addBlackList":"addBlackList",
    "addWhiteList":"addWhiteList",


    "contentM":"Content Management",
    "currentContent":"Current Content",
    "historyContent":"History Content",
    "contentOTT":"OTTContent management",
    "contentWaiting":"Content waiting",
    "contentInject":"Content Inject",
    "contentSynchro":"Content Synchro",
    "contentDistribute":"Content Distribute",
    "contentUpate":"Content Upate",
    "contentDelete":"Content Delete",
    "contentOTTInject":"OTTContent Inject",
    "contentOTTDistribute":"OTTContent Distribute",
    "contentOTTUpate":"OTTContent Upate",
    "contentOTTDelete":"OTTContent Delete",
    "inject":"inject",
    "injectMore":"injectMore",
    "synchroMore":"synchroMore",
    "distribute":"distribute",
    "distributeMore":"distributeMore",
    "update":"update",
    "updateMore":"updateMore",
    "cpId":"CPID",
    "contentList":"contentList",
    "contentUrl":"contentUrl",
    "contentDir":"contentDir",
    "contentId":"contentId",
    "contentName":"contentName",
    "responseType":"responseType",
    "duration":"duration",
    "mimeType":"mimeType",
    "bitRate":"bitRate",
    "size":"size",
    "resolution":"resolution",
    "checkType":"checkType",
    "checkStr":"checkStr",
    "systemId":"systemId",
    "contentType":"contentType",
    "tsSupport":"tsSupport",
    "srcType":"srcType",
    "isFloatIPQAM":"isFloatIPQAM",
    "beginTime":"beginTime",
    "endTime":"endTime",
    "accessURL":"accessURL",
    "providerId":"providerId",
    "needDelivery":"needDelivery",
    "serviceType":"serviceType",
    "mediaType":"mediaType",
    "copyrightStart":"copyrightStart",
    "copyrightEnd":"copyrightEnd",
    "serviceId":"serviceId",
    "onDemand":"on demand",
    "onLive":"on live",
    "support":"support",
    "noSupport":"no support",
    "unicast":"unicast",
    "multicast":"multicast",
    "broadbandVideo":"broadband video",
    "iptvVideo":"IPTV video",
    "movie":"Movie",
    "tvPlay":"TV Play",
    "videoNews":"Video News",
    "videoColumn":"Video Column",
    "distriPriority":"distriPriority",
    "ccsIp":"CCSIP",
    "ccsIpv6":"CCSIPv6",
    "commandType":"commandType",
    "contentUrlDir":"contentUrlDir",
    "operationResult":"operationResult",
    "contentInjectionReq":"contentInjectionReq",
    "contentInjectionBatchReq":"contentInjectionBatchReq",
    "contentDistributeReq":"contentDistributeReq",
    "contentDistributeBatchReq":"contentDistributeBatchReq",
    "contentSynchronizationReq":"contentSynchronizationReq",
    "contentSynchronizationBatchReq":"contentSynchronizationBatchReq",
    "contentUpdateReq":"contentUpdateReq",
    "contentUpdateBatchReq":"contentUpdateBatchReq",
    "contentDeleteReq":"contentDeleteReq",
    "contentDeleteBatchReq":"contentDeleteBatchReq",
    "contentQueryReq":"contentQueryReq",
    "OTTContentInjectionReq":"OTTContentInjectionReq",
    "OTTContentDistributeReq":"OTTContentDistributeReq",
    "OTTContentUpdateReq":"OTTContentUpdateReq",
    "OTTContentDeleteReq":"OTTContentDeleteReq",
    "progress":"progress",
    "success":"success",
    "fail":"fail",
    "unknown":"unknown",
    "running":"running",
    "msgSuccess":"msg send success",
    "sameContent":"same content exist",
    "msgFail":"msg send fail",
    "msgSend":"msg has send",
    "msgCancel":"msg has cancel",
    "delayedIssued":"delayed issued",
    "message":"message",
    "streamingNo":"streamingNo",
    "cmsId":"cmsId",
    "urlType":"urlType",
    "urlType_1":"Content download address",
    "urlType_2":"Content upload address",
    "tsDuration":"tsDuration",
    "rdSupport":"rdSupport",
    "rdDuration":"rdDuration",
    "item1":"item1",
    "item2":"item2",
    "label":"label",
    "iptvChannelType":"iptvChannelType",
    "iptvChannelType_0":"TS/UDP unicast inflow",
    "iptvChannelType_1":"TS/UDP multicast inflow",
    "iptvChannelMulticastIP":"iptvChannelMulticastIP",
    "iptvChannelMulticastPort":"iptvChannelMulticastPort",
    "ingestType":"ingestType",
    "ingestType_1":"cache",
    "ingestType_2":"trust",
    "targetSystemId":"targetSystemId",
    "deleteMethod":"deleteMethod",
    "force":"force delete",
    "graceful":"graceful delete",
    "injecting":"content injecting",
    "synchroing":"content synchroing",
    "distributing":"content distributing",
    "updating":"content updating",
    "deleting":"content deleting",
    "type_text":"Please import text file",
    "import_tip0":"Import txt file，one record per row，spaces are separated by spaces(flag:0-contentUrl  1-contentDir)",
    "import_tip1":"content example：contentId contentName flag URL(txt must has 4 cols,null is - )",
    "import_tip2":"content example：contentId flag URL(txt must has 3 cols,null is - )",
    "import_tip3":"content example：contentId  contentName  contentUrl",
    "selectFail":"Please select a failed record",
    "flag":"flag",
    "inject_tip1":"The number of imported entries does not exceed 1000",
    "inject_tip2":"You cannot have the same contentUrl or dirUrl",
    "fileIsRuning":"Files is being processed",

    "contentQuery":"Content Query",
    "contentSize":"contentSize",
    "cacheTime":"cacheTime",
    "noQueryContent":"No queryContent",
    "fuzzyContentQuery":"fuzzyContentQuery",
    "accurateContentQuery":"accurateContentQuery",

    "badInfo":"Dad Info",
    "ipList":"ipList",
    "ipv4":"ipv4",
    "ipv6":"ipv6",
    "url":"url",
    "badDomain":"Dad Domain",
    "policyVersion":"policyVersion",
    "hostList":"hostList",
    "redirectURL":"redirectURL",
    "bypassUrlParam":"bypassUrlParam",
    "bypassRefererHost":"bypassRefererHost",

    "policyConfig":"Policy Config",
    "delayedStartTime":"delayedStartTime",
    "dailyTime":"dailyTimeRange",
    "delayedHours":"delayedHours",
    "dailyEndTime":"dailyEndTime",
    "policyType":"policyType",
    "policyType_0":"defaultPolicy",
    "policyType_1":"delayedPolicy",
    "effectiveTime":"effectiveTime",
    "distributeNodes":"distributeNodes",
    "syncNodes":"syncNodes",
    "default_policy_exist":"DefaultPolicy is existed",
    "injectType":"injectType",
    "injectType_0":"Immediate inject",
    "injectType_1":"Delayed inject",
    "injectType_2":"Daily inject",
    "injectPolicy":"injectPolicy",
    "distributePolicy":"distributePolicy",
    "synchroPolicy":"synchroPolicy",
    "content":"content",
    "forbidden":"forbidden",
    "forbiddenAll":"forbiddenAll",


    "hotDomain":"Hot Domain",
    "topNumber":"topNumber",
    "sortType":"sortType",
    "sortType_1":"Number of visits",
    "sortType_2":"Service flow",
    "sortType_3":"Backsource flow",
    "sortType_4":"Request hit ratio",
    "sortType_5":"Byte hit ratio",
    "sortType_6":"Average user access rate",
    "domainRank":"domainRank",
    "accessNumber":"accessNumber",
    "serviceTraffic":"serviceTraffic",
    "downTraffic":"downTraffic",
    "requestHitRate":"requestHitRate",
    "byteHitRate":"byteHitRate",
    "userAccessRate":"userAccessRate",

    "singleDomain":"Single Domain",
    "domainView":"Domain View",
    "domainType":"domainType",
    "domainGroup_1":"CDN scenario,signing domain name,CNAME based global scheduling by TCS",
    "domainGroup_2":"CDN scenario,signed domain name,based on DNS forward mode,TCS for global scheduling",
    "domainGroup_3":"WebCache scenario,unsigned domain name,DNS Forward,TCS domain name whitelist",
    "domainGroup_4":"WebCache scenario,unsigned domain name,DNS Forward,TCS domain name blacklist",
    "domainGroup_5":"WebCache scene,unsigned domain name,white list of domain names monitored and scheduled by service nodes locally",
    "domainGroup_6":"WebCache scene,unsigned domain name,blacklist of domain names monitored and scheduled by service nodes locally",


    "pAnReport":"Province and node report",
    "reportDetail":"reportDetail",
    "reportTrend":"reportTrend",
    "pAn_sort":{
        "accessTimes":"accessTimes",
        "userFlow":"userFlow",
        "sourceFlow":"sourceFlow",
        "hitCountPercent":"hitCountPercent",
        "hitFlowPercent":"hitFlowPercent",
        "bandWidth":"bandWidth",
        "peckBandWidth":"peckBandWidth",
        "sourceBandWidth":"sourceBandWidth",
        "gainsRate":"gainsRate",
        "byteHit":"byteHit",
        "hit":"hit",
        "firstByteHitTime":"firstByteHitTime",
        "requestSuccessRate":"requestSuccessRate",
        "sourceRequestSuccessRate":"sourceRequestSuccessRate"
    },
    "oneDay":"one Day",
    "nodeIds":"nodeIds",
    "topNum":"topNum",
    "avgBandWidth":"avgBandWidth",
    "peckBandWidth":"peckBandWidth",
    "flow":"flow",
    "userFlow":"userFlow",
    "avgSourceBandWidth":"avgSourceBandWidth",
    "peckSourceBandWidth":"peckSourceBandWidth",
    "sourceFlow":"sourceFlow",
    "cpuUseRate":"cpuUseRate",
    "peckCpuUseRate":"peckCpuUseRate",
    "memoryUseRate":"memoryUseRate",
    "peckMemoryUseRate":"peckMemoryUseRate",
    "diskUseRate":"diskUseRate",
    "hitRate":"hitRate",
    "minute":"minute",
    "np_resultType0":"all",
    "np_resultType1":"single",
    "diskUse":"diskUse",
    "diskTotal":"diskTotal",
    "avgBandWidthUsage":"avgBandWidthUsage",
    "peakBandWidthUsage":"peakBandWidthUsage",
    "hitRate1":"hitRates",
    "internalLinkPingDelay":"internalLinkPingDelay",
    "packetLossRate":"packetLossRate",
    "jitter":"jitter",
    "timeGranularity":"times",
    "resultType":"resultType",
    "timeOver":"The time limit is over a month",

    "cAdReport":"CP and domain report",
    "cd_resultType0":"all",
    "cd_resultType1":"single",

    "cAnReport":"CP and nodereport",
    "cApReport":"CP and province report",
    "businessType":"businessType",

    "logReportU":"Unified LogReport",
    "area":"area",
    "log_sortType1":"accessTimes",
    "log_sortType2":"userFlow",
    "log_sortType3":"sourceFlow",
    "log_sortType4":"hitCountPercent",
    "log_sortType5":"hitCountByte",
    "log_sortType6":"userAvgSpeed",
    "log_sortType7":"peckBandWidth",
    "accessTimes":"accessTimes",
    "bandWidth":"bandWidth",
    "userBandWidth":"userBandWidth",
    "sourceBandWidth":"sourceBandWidth",
    "gainsRate":"gainsRate",
    "hitCountPercent":"hitCountPercent",
    "bigFileDownloadWidth":"bigFileDownloadWidth",
    "sourceSuccessRate":"sourceSuccessRate",

    "boc":"Bo Ce",
    "resource":"Resource flowRate",
    "cacheContent":"Cache content",
    "configPolicy":"Config policy",
    "cacheConfig":"Cache config",
    "urlConfigErr":"Url configuration error",


    "operateLogQuery":"Operation Log",
    "increase":"increase",
    "increaseMore":"increaseMore",
    "operator":"operator",
    "operationType":"operationType",
    "objectKeyWord":"objectKeyWord",
    "objectName":"objectName",
    "operateContent":"content",
    "operateResult":"result",
    "extraMessage":"extraMessage",
    "costTime":"costTime",
    "comment":"comment",
    "details":"details",
    "noDetails":"noDetails",
    "startTime":"startTime",
    "attrName":"attrName",
    "attrDescMain":"attrDescMain",
    "attrDescExtra":"attrDescExtra",
    "oldValue":"oldValue",
    "newValue":"newValue",

    "securityLog":"Security Log",
    "loginOut":"loginOut",


    "userM":"User Management",
    "enable":"enable",
    "createUser":"createUser",
    "email":"email",
    "telephone":"telephone",
    "confirmPassword":"confirmPassword",
    "description":"description",
    "password_inconsistent":"Password is inconsistent",
    "isResetPsd":"Do you want to reset password？",
    "isEnable":"Do you want to enabled？",
    "enable_S":"enabled success",
    "enable_F":"enabled fail",
    "isStop":"Do you want to stop？",
    "stop_S":"stop success",
    "stop_F":"stop fail",
    "resetPsd":"reset password",
    "christen":"christen",
    "stopped":"stopped",
    "noDelSysadmin":"Cannot delete sysadmin",
    "userORrole":"userName(roleName)",


    "roleM":"Role Management",
    "roleName":"roleName",
    "rolePermissions":"rolePermissions",
    "noMenu":"The user does not have menu privileges",
    "queryKey":"queryKey",
    

    "modifyPsd":"Modify Password",
    "oldPassword":"oldPassword",
    "newPassword":"newPassword",
    "oldPsdErr":"OldPassword is error",
    "modifyPsd_S":"Modify password success",
    "modifyPsd_F":"Modify password fail",
    "reset":"reset",
    "isReset":"Do you want to resest？",
    "reset_S":"reset success",
    "reset_F":"reset fail",

    "onlineUser":"Online User",
    "loginTime":"loginTime",


    "configQuery":"Config Query",
    "receiveConfig":"Receive Config",
    "sendConfig":"Send Config",
    "filePath":"filePath",
    "respCode":"respCode",
    "errorMessage":"errorMessage",
    "transactionID":"transactionID",

    "archiveManagement":"Archive Management",
    "tableName":"tableName",
    "dateLimit":"dateLimit(Day)",
    "countLimit":"countLimit(Page)",
    "elementName":"elementName",

    "systemM":"systemConfig",
    "key":"key",
    "value":"value",
    "defaultValue":"defaultValue",


    "units":{
        "wan":"wan",
        "yi":"yi"
    },


    "nodeType":"nodeType",
    "nodeType_1":"OMS",
    "nodeType_2":"TCS",
    "nodeType_3":"GCS",
    "nodeType_4":"Network CCS",
    "nodeType_5":"Province SNS",
    "nodeType_6":"CRS",
    "nodeType_7":"Main LTC",
    "nodeType_8":"Province CCS",
    "nodeType_9":"City SNS",
    "nodeType_10":"Province CCS_SNS",
    "nodeType_11":"WebCache system",
    "nodeType_12":"Backups LTC",
    "nodeType_13":"County SNS",
    "nodeType_14":"IBS",
    "nodeType_0":"OTHER",


    "device":"device",
    "deviceIP":"deviceIP",
    "deviceIPv6":"deviceIPv6",
    "deviceName":"deviceName",
    "deviceType":"deviceType",
    "deviceType_1":"Management server",
    "deviceType_2":"Global scheduling server",
    "deviceType_3":"Local load balancing device",
    "deviceType_4":"Local DNS scheduling server",
    "deviceType_5":"Local HTTP scheduling server",
    "deviceType_6":"Big file cache server",
    "deviceType_7":"Small file cache server",
    "deviceType_8":"Local network server",
    "deviceType_9":"Local business server",
    "other":"other",


    "serviceMode":"serviceMode",
    "serviceMode_0":"Mixed mode",
    "serviceMode_1":"Webcache mode",
    "serviceMode_2":"CDN mode",
    "serviceMode_3":"Video mode",
    "serviceMode_4":"LTC",


    "contentMode":"contentMode",
    "contentMode_0":"Mixed mode",
    "contentMode_1":"big files",
    "contentMode_2":"small file",
    "contentMode_3":"video",

    "dispatchType":"dispatchType",
    "dispatchType_1":"L4/L7 load balancing",
    "dispatchType_2":"Application layer redirection",

    "groupType":"groupType",
    "groupType_0":"other",
    "groupType_1":"CDN big file",
    "groupType_2":"CDN small file",
    "groupType_3":"WebCache big file",
    "groupType_4":"WebCache small file",
    "groupType_5":"Video group",
    

    "city":"city",
    "citys":{
        "010":"Beijing",
        "021":"Shanghai",
        "022":"Tianjin",
        "023":"Chongqing",
        "024":"Shenyang",
        "0299":"Xiongan New Area",
        "0310":"Handan",
        "0311":"Shijiazhuang",
        "0312":"Baoding",
        "0313":"Zhangjiakou",
        "0314":"Chengde",
        "0315":"Tangshan",
        "0316":"Langfang",
        "0317":"Cangzhou",
        "0318":"Hengshui",
        "0319":"Xingtai",
        "0335":"Qinghuangdao",
        "0349":"Shuozhou",
        "0350":"Xinzhou",
        "0351":"Taiyuan",
        "0352":"Datong",
        "0353":"Yangquan",
        "0354":"Jinzhong",
        "0355":"Changzhi",
        "0356":"Jincheng",
        "0357":"Linfen",
        "0358":"Lvliang",
        "0359":"Yuncheng",
        "0370":"Shangqiu",
        "0371":"Zhengzhou",
        "0372":"Anyang",
        "0373":"Xinxiang",
        "0374":"Xuchang",
        "0375":"Pingdingshan",
        "0376":"Xinyang",
        "0377":"Nanyang",
        "0378":"Kaifeng",
        "0379":"Luoyang",
        "0391":"Jiaozuo",
        "0392":"Hebi",
        "0393":"Puyang",
        "0394":"Zhoukou",
        "0395":"Luohe",
        "0396":"Zhumadian",
        "0397":"Jiyuan",
        "0398":"Sanmenxia",
        "0410":"Tieling",
        "0411":"Dalian",
        "0412":"Anshan",
        "0413":"Fushun",
        "0414":"Benxi",
        "0415":"Dandong",
        "0416":"Jinzhou",
        "0417":"Yingkou",
        "0418":"Fuxin",
        "0419":"Liaoyang",
        "0421":"Chaoyang",
        "0427":"Panjin",
        "0429":"Huludao",
        "0431":"Changchun",
        "0432":"Jilin",
        "0433":"Yanbian",
        "0434":"Siping",
        "0435":"Tonghua",
        "0436":"Baicheng",
        "0437":"Liaoyuan",
        "0438":"Songyuan",
        "0439":"Baishan",
        "0451":"Harbin",
        "0452":"Qiqihar",
        "0453":"Mudanjiang",
        "0454":"Jiamusi",
        "0455":"Suihua",
        "0456":"Heihe",
        "0457":"Daxinanling",
        "0458":"Yichun",
        "0459":"Daqing",
        "0464":"Qitaihe",
        "0467":"Jixi",
        "0468":"Hegang",
        "0469":"Shuangyashan",
        "0470":"Hailar",
        "0471":"Hohehot Municipality",
        "0472":"Baotou",
        "0473":"Wuhai",
        "0474":"Jining",
        "0475":"Tongliao",
        "0476":"Chifeng",
        "0477":"Erdos",
        "0478":"Linhe",
        "0479":"Xilinhot",
        "0482":"Ulanhot",
        "0483":"Bayanhot",
        "025":"Nanjing",
        "0510":"Wuxi",
        "0511":"Zhenjiang",
        "0512":"Suzhou",
        "0513":"Nantong",
        "0514":"Yangzhou",
        "0515":"Yencheng",
        "0516":"Xuzhou",
        "0517":"Huaian",
        "0518":"Lianyungang",
        "0519":"Changzhou",
        "0523":"Taizhou",
        "0527":"Suqian",
        "0530":"Heze",
        "0531":"Jinan",
        "0532":"Qingdao",
        "0533":"Zibo",
        "0534":"Dezhou",
        "0535":"Yantai",
        "0536":"Weifang",
        "0537":"Jining",
        "0538":"Taian",
        "0539":"Linyi",
        "0543":"Binzhou",
        "0546":"Dongying",
        "0631":"Weihai",
        "0632":"Zaozhuang",
        "0633":"Rizhao",
        "0634":"Laiwu",
        "0635":"Liaocheng",
        "0550":"Chuzhou",
        "0551":"Hefei",
        "0552":"Bengbu",
        "0553":"Wuhu",
        "0554":"Huainan",
        "0555":"Ma'anshan",
        "0556":"Anqing",
        "0557":"Suzhou",
        "0558":"Fuyang",
        "0559":"Huangshan",
        "0561":"Huaibei",
        "0562":"Tongling",
        "0563":"Xuancheng",
        "0564":"Lu'an",
        "0566":"Chizhou",
        "0567":"Bozhou",
        "0570":"Quzhou",
        "0571":"Hangzhou",
        "0572":"Huzhou",
        "0573":"Jiaxing",
        "0574":"Ningbo",
        "0575":"Shaoxing",
        "0576":"Taizhou",
        "0577":"Wenzhou",
        "0578":"Lishui",
        "0579":"Jinhua",
        "0580":"Zhoushan",
        "0591":"Fuzhou",
        "0592":"Xiamen",
        "0593":"Ningde",
        "0594":"Putian",
        "0595":"Quanzhou",
        "0596":"Zhangzhou",
        "0597":"Longyan",
        "0598":"Sanming",
        "0599":"Nanping",
        "020":"Guangzhou",
        "0660":"Shanwei",
        "0662":"Yangjiang",
        "0663":"Jieyang",
        "0668":"Maoming",
        "0750":"Jiangmen",
        "0751":"Shaoguan",
        "0752":"Huizhou",
        "0753":"Meizhou",
        "0754":"Shantou",
        "0755":"Shenzhen",
        "0756":"Zhuhai",
        "0757":"Foshan",
        "0758":"Zhaoqing",
        "0759":"Zhanjiang",
        "0760":"Zhongshan",
        "0762":"Heyuan",
        "0763":"Qingyuan",
        "0766":"Yunfu",
        "0768":"Chaozhou",
        "0769":"Dongguan",
        "027":"Wuhan",
        "0721":"Tianmen",
        "0720":"Jianghan",
        "0710":"Xiangfan",
        "0711":"Ezhou",
        "0712":"Xiaogan",
        "0713":"Huanggang",
        "0714":"Huangshi",
        "0715":"Xianning",
        "0716":"Jingzhou",
        "0717":"Yichang",
        "0718":"Enshi",
        "0719":"Shiyan",
        "0722":"Suizhou",
        "0724":"Jingmen",
        "0728":"Qianjiang",
        "0730":"Yueyang",
        "0731":"Changsha",
        "0732":"Xiangtan",
        "0733":"Zhuzhou",
        "0734":"Hengyang",
        "0735":"Chenzhou",
        "0736":"Changde",
        "0737":"Yiyang",
        "0738":"Loudi",
        "0739":"Shaoyang",
        "0743":"Jishou",
        "0744":"Zhangjiajie",
        "0745":"Huaihua",
        "0746":"Yongzhou",
        "0770":"Fangzcwngzgang",
        "0771":"Nanning",
        "0772":"Liuzhou",
        "0773":"Guilin",
        "0774":"Wuzhou",
        "0775":"Yulin",
        "0776":"Baise",
        "0777":"Qinzhou",
        "0778":"Hechi",
        "0779":"Beihai",
        "0780":"Chongzuo",
        "0781":"Laibin",
        "0782":"Guigang",
        "0783":"Hezhou",
        "0701":"Yingtan",
        "0790":"Xinyu",
        "0791":"Nanchang",
        "0792":"Jiujiang",
        "0793":"Shangrao",
        "0794":"Fuzhou",
        "0795":"Yichun",
        "0796":"Ji'an",
        "0797":"Ganzhou",
        "0798":"Jingdezhen",
        "0799":"Pingxiang",
        "028":"Chengdu",
        "0812":"Panzhihua",
        "0813":"Zigong",
        "0816":"Mianyang",
        "0817":"Nanchong",
        "0818":"Dazhou",
        "0825":"Suining",
        "0826":"Guang'an",
        "0827":"Bazhong",
        "0830":"Luzhou",
        "0831":"Yibin",
        "0832":"Neijiang",
        "0283":"Ziyang",
        "0833":"Leshan",
        "0282":"Meishan",
        "0834":"Liangshan",
        "0835":"Ya'an",
        "0836":"Ganzi",
        "0837":"Ngawa",
        "0838":"Deyang",
        "0839":"Guangyuan",
        "0850":"Guian new area",
        "0851":"Guiyang",
        "0852":"Zunyi",
        "0853":"Anshun",
        "0854":"Tuyun",
        "0855":"Kaili",
        "0856":"Tongren",
        "0857":"Bijie",
        "0858":"Liupanshui",
        "0859":"Xingyi",
        "0691":"Banna", 
        "0692":"Dehong",
        "0870":"Zhaotong",
        "0871":"Kunming",
        "0872":"Dali",
        "0873":"Honghe",
        "0874":"Qujing",
        "0875":"Baoshan",
        "0876":"Wenshan",
        "0877":"Yuxi",
        "0878":"Chuxiong",
        "0879":"Simao",
        "0883":"Lincang",
        "0886":"Nujiang",
        "0887":"Diqing",
        "0888":"Lijiang",
        "0891":"Lhasa",
        "0892":"Shigatse",
        "0893":"Shannan",
        "0894":"Linzhi",
        "0895":"Changdu",
        "0896":"Nagqu",
        "0897":"Ali",
        "0898":"Haikou",
        "029":"Xi'an",
        "0910":"Xianyang",
        "0911":"Yan'an",
        "0912":"Yulin",
        "0913":"Weinan",
        "0914":"Shangluo",
        "0915":"Ankang",
        "0916":"Hanzhoung",
        "0917":"Baoji",
        "0919":"Tongchuan",
        "0930":"Linxia",
        "0931":"Lanzhou",
        "0932":"Dingxi",
        "0933":"Pingliang",
        "0934":"Qingyang",
        "0935":"Wuwei, Jinchang",
        "0936":"Zhangye",
        "0937":"Jiayuguan Pass",
        "0938":"Tianshui",
        "0939":"Longnan",
        "0941":"Gannan",
        "0943":"Baiyin",
        "0951":"Yinchuan",
        "0952":"Shizuishan",
        "0953":"Wuzhong",
        "0954":"Guyuan",
        "0955":"Zhongwei",
        "0970":"Haiyan",
        "0971":"Xining",
        "0972":"Haidong",
        "0973":"Huangnan",
        "0974":"Gonghe",
        "0975":"Goulou",
        "0976":"Yushu",
        "0977":"Delingha",
        "0979":"Golmud",
        "0901":"Tacheng",
        "0902":"Hami",
        "0903":"Hetian",
        "0906":"Aletai",
        "0908":"Kezhou",
        "0909":"Bole",
        "0990":"Karamay",
        "0991":"Urumchi",
        "0992":"Kuitun",
        "0993":"Shihezi",
        "0994":"Changji",
        "0995":"Turpan",
        "0996":"Korla",
        "0997":"Akesu",
        "0998":"Kashgar",
        "0999":"Ili"
    },
    "province":"province",
    "BJ":"Beijing",
    "TJ":"Tianjin",
    "HE":"Hebei",
    "SX":"Shanxi",
    "NM":"Neimeng",
    "LN":"Liaolin",
    "JL":"Jilin",
    "HL":"Heilongjiang",
    "SH":"Shanghai",
    "JS":"Jiangsu",
    "ZJ":"Zhejiang",
    "AH":"Anhu",
    "FJ":"Fujian",
    "JX":"Jiangxi",
    "SD":"Shandong",
    "HA":"Henan",
    "HB":"Hubei",
    "HN":"Hunan",
    "GD":"Guangdong",
    "HI":"Hainan",
    "GX":"Guangxi",
    "CQ":"Chongqin",
    "SC":"Sichuan",
    "GZ":"Guizhou",
    "YN":"Yunnan",
    "SN":"Shanxi",
    "GS":"Gansu",
    "QH":"Qinghai",
    "NX":"Ningxia",
    "XJ":"Xinjiang",
    "XZ":"Xizang",

    "cacheFirm":"cacheFirm",
    "HW":"Huawei",
    "ZTE":"ZTE",
    "FH":"FiberHome",
    "CMHI":"CMHI",

    "cacheType_0":"Undistinguished",
    "cacheType_1":"WEB small file",
    "cacheType_2":"HTTP big files",
    "cacheType_3":"P2P video",

    "userAccessType_0":"Undistinguished",
    "userAccessType_1":"Special line",
    "userAccessType_2":"2/3/4G",
    "userAccessType_3":"Family bandwidth",
    "userAccessType_4":"WLAN",

    "userTerminalType_0":"Undistinguished",
    "userTerminalType_1":"Phone",
    "userTerminalType_2":"PAD",
    "userTerminalType_3":"PC",

    "alarmType":"alarmType",
    "alarmType_1":"Fault alarm",
    "alarmType_2":"Clear alarm",
    "alarmType_3":"Event alarm",

    "alarmLevel":"AlarmLevel",
    "alarmLevel_1":"Tips",
    "alarmLevel_2":"Alarm",
    "alarmLevel_3":"Serious",
    "alarmLevel_4":"Lethal",

    "resCode_0":"OK",
    "resCode_1":"BAD_REQUEST",
    "resCode_2":"UNAUTHORIZED",
    "resCode_3":"FORBIDDEN",
    "resCode_4":"REQUEST_OVERLOAD",


    "pleaseInput":"Please input",
    "pleaseInputNumber":"Please input number",
    "pleaseInputUserName":"Please input userName",
    "pleaseInputPwd":"Please input password",
    "pleaseInputPwdAgain":"Please input password again",
    "pleaseInputOldPwd":"Please input old password",
    "pleaseInputNewPwd":"Please input new password",
    "pleaseInputNewPwdAgain":"Please input new password again",
    "pleaseInputIPv4":"Please input IPv4",
    "pleaseInputIPv6":"Please input IPv6",
    "pleaseSelectTime":"Please select time",
    "beginToEnd":"startTime ~ endTime",
    "nameTip":"Enter only numbers below 64 bits, capitals and underscores in English",
    "passwordTip":"Only 6-18 digits, capitals and underscores are supported",
    "beNumber":"Please input number",
    "beNumber_10":"Please input number less than 10 bits",
    "beNumber_25":"Please input number less than 25 bits",
    "invalidIpv4":"Please input valid IPv4",
    "invalidIpv6":"Please input valid IPv6",
    "invalidTel":"Please input valid telephone",
    "invalidemail":"Please input valid mail ",
    "invalidPort":"Please input the integer of [0,65535]",
    "invalidTimeTip":"Please input the integer of [0,86400]"
  
}